pymdoccbor/__init__.py
pymdoccbor/exceptions.py
pymdoccbor/settings.py
pymdoccbor/tools.py
pymdoccbor/x509.py
pymdoccbor/mdoc/__init__.py
pymdoccbor/mdoc/exceptions.py
pymdoccbor/mdoc/issuer.py
pymdoccbor/mdoc/issuersigned.py
pymdoccbor/mdoc/verifier.py
pymdoccbor/mso/__init__.py
pymdoccbor/mso/issuer.py
pymdoccbor/mso/verifier.py
pymdoccbor/tests/__init__.py
pymdoccbor/tests/cert_data.py
pymdoccbor/tests/micov_data.py
pymdoccbor/tests/pid_data.py
pymdoccbor/tests/pkey.py
pymdoccbor/tests/test_01_mdoc_parser.py
pymdoccbor/tests/test_02_mdoc_issuer.py
pymdoccbor/tests/test_03_mdoc_issuer.py
pymdoccbor/tests/test_04_issuer_signed.py
pymdoccbor/tests/test_05_mdoc_verifier.py
pymdoccbor/tests/test_06_mso_issuer.py
pymdoccbor/tests/test_07_mso_verifier.py
pymdoccbor/tests/test_08_mdoc_cbor.py
pymdoccbor/tests/test_09_errors_field.py
pymdoccbor/tests/test_10_cert_chain_and_hashes.py
pymdoccbor-1.1.0.dist-info/licenses/LICENSE
pymdoccbor-1.1.0.dist-info/METADATA
pymdoccbor-1.1.0.dist-info/WHEEL
pymdoccbor-1.1.0.dist-info/top_level.txt
pymdoccbor-1.1.0.dist-info/RECORD
