Metadata-Version: 2.4
Name: pymdoccbor
Version: 1.1.0
Summary: Python parser and writer for Mobile Driving License and EUDI Wallet MDOC CBOR.
Home-page: https://github.com/IdentityPython/pyMDL-MDOC
Author: Giuseppe De Marco
Author-email: demarcog83@gmail.com
License: License :: OSI Approved :: Apache Software License
Classifier: Development Status :: 4 - Beta
Classifier: License :: OSI Approved :: Apache Software License
Classifier: Programming Language :: Python :: 3.10
Classifier: Programming Language :: Python :: 3.11
Classifier: Programming Language :: Python :: 3.12
Classifier: Topic :: Software Development :: Libraries :: Python Modules
License-File: LICENSE
Requires-Dist: cbor2>=5.4.0
Requires-Dist: cbor-diag>=1.1.0
Requires-Dist: pycose>=1.0.1
Dynamic: author
Dynamic: author-email
Dynamic: classifier
Dynamic: description
Dynamic: description-content-type
Dynamic: home-page
Dynamic: license
Dynamic: license-file
Dynamic: requires-dist
Dynamic: summary
